perisso/__init__.py
perisso/collection.py
perisso/connection.py
perisso/core.py
perisso/enums.py
perisso/guid.py
perisso/helper.py
perisso/tapir_commands.py
perisso/type_utils.py
perisso/types.py
perisso/utils.py
perisso-0.6.1.dist-info/METADATA
perisso-0.6.1.dist-info/WHEEL
perisso-0.6.1.dist-info/licenses/LICENSE
perisso-0.6.1.dist-info/RECORD
