Metadata-Version: 2.4
Name: perisso
Version: 0.6.1
Summary: Experimental Tapir utility for supercharging Archicad automation.
Project-URL: Homepage, https://github.com/runxel/perisso
Project-URL: Bug Tracker, https://github.com/runxel/perisso/issues
Author-email: Lucas Becker <lucas@akroter.io>
License-Expression: MIT
License-File: LICENSE
Keywords: archicad,automation,bim,tapir
Classifier: License :: OSI Approved :: MIT License
Classifier: Operating System :: OS Independent
Classifier: Programming Language :: Python :: 3
Requires-Python: >=3.12
Requires-Dist: archicad
